systemstat/__init__.py
systemstat/gridstat3.py
systemstat/gridstat4.py
systemstat/sutstat.py
systemstat/systemstat.py
systemstat-0.1.0.dist-info/entry_points.txt
systemstat-0.1.0.dist-info/LICENSE
systemstat-0.1.0.dist-info/WHEEL
systemstat-0.1.0.dist-info/METADATA
systemstat-0.1.0.dist-info/RECORD
