Metadata-Version: 2.1
Name: systemstat
Version: 0.1.0
Summary: 
Home-page: http://github.com/dskard/systemstat
License: MIT
Author: dskard
Requires-Python: >=3.9,<4.0
Classifier: License :: OSI Approved :: MIT License
Classifier: Programming Language :: Python :: 3
Classifier: Programming Language :: Python :: 3.9
Classifier: Programming Language :: Python :: 3.10
Requires-Dist: requests (>=2.28.1,<3.0.0)
Project-URL: Repository, http://github.com/dskard/systemstat
